bios_pnp/__init__.py
bios_pnp/pnp.py
bios_pnp/vendors.py
bios_pnp-2.0.0.dist-info/LICENSE
bios_pnp-2.0.0.dist-info/METADATA
bios_pnp-2.0.0.dist-info/WHEEL
bios_pnp-2.0.0.dist-info/top_level.txt
bios_pnp-2.0.0.dist-info/RECORD
