Metadata-Version: 2.1
Name: bios-pnp
Version: 2.0.0
Summary: Very simple module that enumerates Legacy Plug and Play devices
Home-page: https://github.com/nicholasbishop/bios_pnp
Author: Nicholas Bishop
Author-email: nicholasbishop@gmail.com
License: Apache 2.0
Platform: UNKNOWN
Requires-Dist: attrs (~=20.1.0)
